rubio/__init__.py
rubio-1.0.1.dist-info/METADATA
rubio-1.0.1.dist-info/WHEEL
rubio-1.0.1.dist-info/top_level.txt
rubio-1.0.1.dist-info/RECORD
