Metadata-Version: 2.4
Name: Rubio
Version: 1.0.1
Summary: The Ultimate Elite Rubika Bot Framework. @RubioLib
Home-page: https://t.me/RubioLib
Author: Rubio Team
Classifier: Programming Language :: Python :: 3
Classifier: License :: OSI Approved :: MIT License
Classifier: Operating System :: OS Independent
Requires-Python: >=3.7
Requires-Dist: httpx
Dynamic: author
Dynamic: classifier
Dynamic: description
Dynamic: description-content-type
Dynamic: home-page
Dynamic: requires-dist
Dynamic: requires-python
Dynamic: summary
